before/__init__.py
before-1.0.2.dist-info/LICENSE
before-1.0.2.dist-info/METADATA
before-1.0.2.dist-info/WHEEL
before-1.0.2.dist-info/RECORD
