Metadata-Version: 2.1
Name: before
Version: 1.0.2
Summary: import from python2
Home-page: https://github.com/tomhea/before
License: BSD-2-Clause-Simplified
Keywords: python2,past
Author: Tom Herman
Author-email: flipjumpproject@gmail.com
Requires-Python: >=3.7,<4.0
Classifier: License :: Other/Proprietary License
Classifier: Operating System :: OS Independent
Classifier: Programming Language :: Python :: 3
Classifier: Programming Language :: Python :: 3.7
Classifier: Programming Language :: Python :: 3.8
Classifier: Programming Language :: Python :: 3.9
Classifier: Programming Language :: Python :: 3.10
Classifier: Programming Language :: Python :: 3.11
Classifier: Programming Language :: Python :: 3.12
Classifier: Programming Language :: Python :: 2
Project-URL: Repository, https://github.com/tomhea/before
